protobuf_serialization/__init__.py
protobuf_serialization/constants.py
protobuf_serialization/utils.py
protobuf_serialization/version.py
protobuf_serialization/deserialization/__init__.py
protobuf_serialization/deserialization/protobuf_to_dict.py
protobuf_serialization/deserialization/utils.py
protobuf_serialization/serialization/__init__.py
protobuf_serialization/serialization/auto.py
protobuf_serialization/serialization/fields.py
protobuf_serialization/serialization/serializer.py
protobuf_serialization-0.1.2.dist-info/LICENSE
protobuf_serialization-0.1.2.dist-info/METADATA
protobuf_serialization-0.1.2.dist-info/WHEEL
protobuf_serialization-0.1.2.dist-info/top_level.txt
protobuf_serialization-0.1.2.dist-info/RECORD
